.gitignore
LICENSE
README.md
setup.py
bin/kubespin
examples/myapp.json
examples/output/app.demo-module.json
examples/output/demo-module.production.deploy.json
examples/output/demo-module.qa.deploy.json
examples/sponnet/application.libsonnet
examples/sponnet/naming.libsonnet
examples/sponnet/pipeline.libsonnet
examples/sponnet/v2PipelineTemplate.libsonnet
examples/templates/applications/default/app.jsonnet
examples/templates/pipelines/default/deploy.jsonnet
kubespin/__init__.py
kubespin/build.py
kubespin/domain.py
kubespin/manifest.py
kubespin/render.py
kubespin.egg-info/PKG-INFO
kubespin.egg-info/SOURCES.txt
kubespin.egg-info/dependency_links.txt
kubespin.egg-info/requires.txt
kubespin.egg-info/top_level.txt